needlr/__init__.py
needlr/_http.py
needlr/client.py
needlr/auth/__init__.py
needlr/auth/auth.py
needlr/auth/scopes.py
needlr/core/__init__.py
needlr/core/capacity/__init__.py
needlr/core/capacity/capacity.py
needlr/core/item/__init__.py
needlr/core/item/item.py
needlr/core/workspace/__init__.py
needlr/core/workspace/identity.py
needlr/core/workspace/role.py
needlr/core/workspace/workspace.py
needlr/dataactivator/__init__.py
needlr/dataactivator/reflex/__init__.py
needlr/dataengineering/__init__.py
needlr/dataengineering/sqlendpoints.py
needlr/datafactory/__init__.py
needlr/datafactory/datapipeline.py
needlr/datascience/__init__.py
needlr/datawarehouse/__init__.py
needlr/datawarehouse/warehouse/__init__.py
needlr/datawarehouse/warehouse/mirroredwarehouse.py
needlr/datawarehouse/warehouse/warehouse.py
needlr/industrysolutions/__init__.py
needlr/models/__init__.py
needlr/models/capacity.py
needlr/models/dashboard.py
needlr/models/datamart.py
needlr/models/datapipeline.py
needlr/models/eventhouse.py
needlr/models/eventstream.py
needlr/models/item.py
needlr/models/kqldatabase.py
needlr/models/kqlqueryset.py
needlr/models/paginatedreport.py
needlr/models/report.py
needlr/models/semanticmodel.py
needlr/models/sqlendpoint.py
needlr/models/warehouse.py
needlr/models/workspace.py
needlr/powerbi/__init__.py
needlr/powerbi/dashboard.py
needlr/powerbi/datamart.py
needlr/powerbi/paginatedreport.py
needlr/powerbi/report.py
needlr/powerbi/semanticmodel.py
needlr/realtimeintelligence/__init__.py
needlr/realtimeintelligence/eventhouse.py
needlr/realtimeintelligence/eventstream.py
needlr/realtimeintelligence/kqldatabase.py
needlr/realtimeintelligence/kqlqueryset.py
needlr/utils/__init__.py
needlr/utils/util.py
tests/__init__.py
tests/conftest.py
needler-0.1.0.dist-info/LICENSE
needler-0.1.0.dist-info/METADATA
needler-0.1.0.dist-info/WHEEL
needler-0.1.0.dist-info/top_level.txt
needler-0.1.0.dist-info/RECORD
